mistro/__init__.py
mistro/core.py
mistro-0.0.1.dist-info/METADATA
mistro-0.0.1.dist-info/WHEEL
mistro-0.0.1.dist-info/top_level.txt
mistro-0.0.1.dist-info/RECORD
