Metadata-Version: 2.4
Name: mistro
Version: 0.0.1
Summary: The SMS orchestration layer for developers.
Requires-Python: >=3.9
